dotdict/__init__.py
dotdict/dotdict.py
dotdict_python-0.0.1.dist-info/LICENSE
dotdict_python-0.0.1.dist-info/METADATA
dotdict_python-0.0.1.dist-info/WHEEL
dotdict_python-0.0.1.dist-info/top_level.txt
dotdict_python-0.0.1.dist-info/RECORD
