Metadata-Version: 2.1
Name: dotdict-python
Version: 0.0.1
Summary: Dot notation access to dictionary attributes
Home-page: UNKNOWN
Author: Ryan Rudes
Author-email: ryanrudes@gmail.com
License: UNKNOWN
Platform: UNKNOWN
Classifier: Programming Language :: Python :: 3
Classifier: License :: OSI Approved :: MIT License
Classifier: Operating System :: OS Independent
Requires-Python: >=3.6
License-File: LICENSE
